os_llm_agents/__init__.py
os_llm_agents/executors.py
os_llm_agents/models.py
os_llm_agents-0.0.1.dist-info/METADATA
os_llm_agents-0.0.1.dist-info/WHEEL
os_llm_agents-0.0.1.dist-info/top_level.txt
os_llm_agents-0.0.1.dist-info/RECORD
