Metadata-Version: 2.1
Name: os-llm-agents
Version: 0.0.1
Summary: Python package that helps to build LLM agents based on open-source models from Huggingface Hub.
Home-page: https://github.com/WSE-research/open-source-llm-agents
Author: Aleksandr Perevalov, Andreas Both
Author-email: aleksandr.perevalov@htwk-leipzig.de,andreas.both@htwk-leipzig.de
License: MIT
Keywords: llm agents huggingface transformers
Platform: UNKNOWN
Classifier: Programming Language :: Python
Classifier: Programming Language :: Python :: 3
Classifier: Programming Language :: Python :: 3.8
Classifier: Programming Language :: Python :: 3.9
Classifier: Programming Language :: Python :: 3.10
Classifier: License :: OSI Approved :: MIT License
Classifier: Operating System :: OS Independent
Requires-Python: >=3.8
Requires-Dist: langchain-core
Requires-Dist: transformers
